fast_multipart-0.1.0.dist-info/METADATA
fast_multipart-0.1.0.dist-info/WHEEL
fast_multipart/__init__.py
fast_multipart/fast_multipart.pyi
fast_multipart/fast_multipart.pypy311-pp73-ppc_64-linux-gnu.so
fast_multipart/py.typed
fast_multipart-0.1.0.dist-info/RECORD
