Metadata-Version: 2.4
Name: fast-multipart
Version: 0.1.0
Classifier: Development Status :: 4 - Beta
Classifier: Programming Language :: Rust
Classifier: Programming Language :: Python :: Implementation :: CPython
Classifier: Programming Language :: Python :: Implementation :: PyPy
Requires-Dist: pytest ; extra == 'tests'
Provides-Extra: tests
Summary: ⚡ Lightning-fast multipart parsing for Python
Author: Aprila Hijriyan <april@kuli.dev>
Author-email: Aprila Hijriyan <april@kuli.dev>
Requires-Python: >=3.9
Project-URL: homepage, https://github.com/aprilahijriyan/fast-multipart
Project-URL: documentation, https://github.com/aprilahijriyan/fast-multipart
Project-URL: repository, https://github.com/aprilahijriyan/fast-multipart
